LICENSE
MANIFEST.in
README.md
setup.cfg
setup.py
melonutils/__init__.py
melonutils/lib.py
melonutils/meta.py
melonutils.egg-info/PKG-INFO
melonutils.egg-info/SOURCES.txt
melonutils.egg-info/dependency_links.txt
melonutils.egg-info/not-zip-safe
melonutils.egg-info/top_level.txt
melonutils/core/__init__.py
melonutils/core/classes.py
melonutils/core/embed.py
melonutils/core/exceptions.py
melonutils/core/helpers.py
melonutils/core/object.py